{
  "version": "5",
  "dialect": "sqlite",
  "id": "5fd9edda-66aa-48a2-a66a-f9c7d12984eb",
  "prevId": "6e991849-8a05-4ef3-8c1a-9736118903e5",
  "tables": {
    "todos": {
      "name": "todos",
      "columns": {
        "id": {
          "name": "id",
          "type": "integer",
          "primaryKey": true,
          "notNull": true,
          "autoincrement": true
        },
        "text": {
          "name": "text",
          "type": "text",
          "primaryKey": false,
          "notNull": false,
          "autoincrement": false
        },
        "done": {
          "name": "done",
          "type": "integer",
          "primaryKey": false,
          "notNull": false,
          "autoincrement": false
        },
        "timestamp": {
          "name": "timestamp",
          "type": "text",
          "primaryKey": false,
          "notNull": false,
          "autoincrement": false
        }
      },
      "indexes": {},
      "foreignKeys": {},
      "compositePrimaryKeys": {},
      "uniqueConstraints": {}
    }
  },
  "enums": {},
  "_meta": {
    "schemas": {},
    "tables": {},
    "columns": {
      "\"todos\".\"name\"": "\"todos\".\"text\"",
      "\"todos\".\"isCompleted\"": "\"todos\".\"done\""
    }
  }
}